Workbook

Sheet Leyenda
A1: Economía unitaria · Descanso Compartido · V2 (13/10/2026)
A2: Ninguna cifra de este libro es un coste o precio real confirmado salvo lo que el titular escriba en la columna REAL con facturas o cotizaciones firmadas.
A4: Cómo usarlo
A5: 1. Celdas AMARILLAS con texto AZUL = datos editables. Texto NEGRO = fórmulas (no sobrescribir). VERDE = enlace a otra hoja.
A6: 2. Columna REAL (hoja Escenarios): rellenar las 5 partidas del coste (filas 7–11). Si falta UNA, la columna muestra «DATOS INCOMPLETOS» y no calcula margen.
A7: 3. Una partida que realmente vale 0 se escribe 0; una celda VACÍA significa «no lo sé» y bloquea el cálculo.
A8: 4. Escenarios 1–5 = hipótesis de los informes (coste agregado). Reproducen 0,56 / 7,04 / 11,54 / 11,03 / 7,14 €.
A9: 5. Veredictos posibles: «Supera umbral (hipótesis)», «No supera (hipótesis)», «Supera umbral», «No supera», «DATOS INCOMPLETOS». Nunca «rentable».
A11: Formato esperado de una fila del panel semanal (ejemplo de FORMATO, no son datos): semana 2026-W43 · sesiones 1.000 · sesiones con vista de producto 400 · con ATC 40 · con checkout 20 · pedidos 10 · ventas brutas 299,00 € …
A13: Fuentes de los supuestos
A14: IVA 21 %: tipo general (AEAT, S25); tipo del SKU pendiente de confirmar por asesoría.
A15: Comisión 2,9 % + 0,30 €: supuesto prudencial de los informes; sustituir por la tarifa real del plan (fila «Comisión real»).
... A17: No incluido: cuota Shopify, apps, gestoría, IRPF y publicidad salvo CAC.

Sheet Supuestos
A1: Supuestos globales
A3: Supuesto | B3: Valor | C3: Fuente / nota
A4: IVA aplicado al PVP (hipótesis) | B4: 0.21 | C4: S25 tipo general; tipo del SKU pendiente (asesoría).
A5: Comisión de pago variable (hipótesis) | B5: 0.029 | C5: Supuesto de los informes.
A6: Comisión de pago fija por pedido (hipótesis) | B6: 0.3 | C6: Supuesto de los informes.
A7: Umbral mínimo de contribución antes de marketing | B7: 7 | C7: Estudio §9.2 (7–8 €).
A8: Capital disponible para pedidos y reembolsos | B8: 50 | C8: Declarado por el titular.
A9: CAC de referencia (hipótesis) | B9: 10 | C9: Estudio §9.2.
A10: Días naturales hasta cobrar la liquidación (hipótesis) | B10: 5 | C10: S27: mínimo 3 días hábiles + banco.

Sheet Escenarios
A1: Contribución por pedido (antes de costes fijos e impuestos directos)
A2: Columnas B–F: hipótesis de los informes. Columna G: REAL (solo datos confirmados).
A3: Concepto | B3: 1. Desfavorable | C3: 2. Base | D3: 3. Mejor logística | E3: 4. PVP superior | F3: 5. Ejemplo Maestro | G3: REAL (confirmado)
A4: PVP con IVA | B4: 24.9 | C4: 29.9 | D4: 29.9 | E4: 34.9 | F4: 29.9
A5: Tipo de columna | B5: HIPÓTESIS | C5: HIPÓTESIS | D5: HIPÓTESIS | E5: HIPÓTESIS | F5: HIPÓTESIS | G5: REAL
A6: Coste agregado (solo hipótesis; no se admite en REAL) | B6: 16 | C6: 14 | D6: 10 | E6: 14 | F6: 14.4 | G6: n/a
A7: · Producto
A8: · Envío a domicilio
A9: · Aranceles / derecho 3 € / importación
A10: · Preparación y embalaje
A11: · Otros costes variables no recuperables
A12: Partidas del desglose rellenadas (de 5) | B12: =COUNT(B7:B11) -> 0 | C12: =COUNT(C7:C11) -> 0 | D12: =COUNT(D7:D11) -> 0 | E12: =COUNT(E7:E11) -> 0 | F12: =COUNT(F7:F11) -> 0 | G12: =COUNT(G7:G11) -> 0
A13: Estado del coste | B13: =IF(B12=5,"DESGLOSE COMPLETO",IF(AND(B12=0,B6<>""),"HIPÓTESIS (agregado)","DATOS INCOMPLETOS")) -> HIPÓTESIS (agregado) | C13: =IF(C12=5,"DESGLOSE COMPLETO",IF(AND(C12=0,C6<>""),"HIPÓTESIS (agregado)","DATOS INCOMPLETOS")) -> HIPÓTESIS (agregado) | D13: =IF(D12=5,"DESGLOSE COMPLETO",IF(AND(D12=0,D6<>""),"HIPÓTESIS (agregado)","DATOS INCOMPLETOS")) -> HIPÓTESIS (agregado) | E13: =IF(E12=5,"DESGLOSE COMPLETO",IF(AND(E12=0,E6<>""),"HIPÓTESIS (agregado)","DATOS INCOMPLETOS")) -> HIPÓTESIS (agregado) | F13: =IF(F12=5,"DESGLOSE COMPLETO",IF(AND(F12=0,F6<>""),"HIPÓTESIS (agregado)","DATOS INCOMPLETOS")) -> HIPÓTESIS (agregado) | G13: =IF(OR(G4="",G12<5,G15="",G16="",G17=""),"DATOS INCOMPLETOS","COMPLETO") -> DATOS INCOMPLETOS
A14: Coste completo usado | B14: =IF(B13="DATOS INCOMPLETOS","—",IF(B12=5,SUM(B7:B11),B6)) -> 16 | C14: =IF(C13="DATOS INCOMPLETOS","—",IF(C12=5,SUM(C7:C11),C6)) -> 14 | D14: =IF(D13="DATOS INCOMPLETOS","—",IF(D12=5,SUM(D7:D11),D6)) -> 10 | E14: =IF(E13="DATOS INCOMPLETOS","—",IF(E12=5,SUM(E7:E11),E6)) -> 14 | F14: =IF(F13="DATOS INCOMPLETOS","—",IF(F12=5,SUM(F7:F11),F6)) -> 14.4 | G14: =IF(G13="DATOS INCOMPLETOS","—",IF(G12=5,SUM(G7:G11),G6)) -> —
A15: Reserva incidencias y soporte por pedido | B15: 3 | C15: 2.5 | D15: 2 | E15: 2.5 | F15: 2
A16: Coste esperado de devoluciones por pedido | B16: 0 | C16: 0 | D16: 0 | E16: 0 | F16: 0
A17: Coste de contenido / colaboradores por venta | B17: 0 | C17: 0 | D17: 0 | E17: 0 | F17: 0
A18: Comisión real % (vacío = usar supuesto)
A19: PVP sin IVA | B19: =IF(B4="","—",B4/(1+Supuestos!$B$4)) -> 20.578512 | C19: =IF(C4="","—",C4/(1+Supuestos!$B$4)) -> 24.710744 | D19: =IF(D4="","—",D4/(1+Supuestos!$B$4)) -> 24.710744 | E19: =IF(E4="","—",E4/(1+Supuestos!$B$4)) -> 28.842975 | F19: =IF(F4="","—",F4/(1+Supuestos!$B$4)) -> 24.710744 | G19: =IF(G4="","—",G4/(1+Supuestos!$B$4)) -> —
A20: Comisión de pago | B20: =IF(B4="","—",B4*IF(B18="",Supuestos!$B$5,B18)+Supuestos!$B$6) -> 1.0221 | C20: =IF(C4="","—",C4*IF(C18="",Supuestos!$B$5,C18)+Supuestos!$B$6) -> 1.1671 | D20: =IF(D4="","—",D4*IF(D18="",Supuestos!$B$5,D18)+Supuestos!$B$6) -> 1.1671 | E20: =IF(E4="","—",E4*IF(E18="",Supuestos!$B$5,E18)+Supuestos!$B$6) -> 1.3121 | F20: =IF(F4="","—",F4*IF(F18="",Supuestos!$B$5,F18)+Supuestos!$B$6) -> 1.1671 | G20: =IF(G4="","—",G4*IF(G18="",Supuestos!$B$5,G18)+Supuestos!$B$6) -> —
A21: Contribución por pedido | B21: =IF(B13<>"DATOS INCOMPLETOS",B19-B14-B15-B16-B17-B20,"DATOS INCOMPLETOS") -> 0.5564124 | C21: =IF(C13<>"DATOS INCOMPLETOS",C19-C14-C15-C16-C17-C20,"DATOS INCOMPLETOS") -> 7.0436438 | D21: =IF(D13<>"DATOS INCOMPLETOS",D19-D14-D15-D16-D17-D20,"DATOS INCOMPLETOS") -> 11.543644 | E21: =IF(E13<>"DATOS INCOMPLETOS",E19-E14-E15-E16-E17-E20,"DATOS INCOMPLETOS") -> 11.030875 | F21: =IF(F13<>"DATOS INCOMPLETOS",F19-F14-F15-F16-F17-F20,"DATOS INCOMPLETOS") -> 7.1436438 | G21: =IF(G13<>"DATOS INCOMPLETOS",G19-G14-G15-G16-G17-G20,"DATOS INCOMPLETOS") -> DATOS INCOMPLETOS
A22: Veredicto frente al umbral | B22: =IF(B13<>"DATOS INCOMPLETOS",IF(B21>=Supuestos!$B$7,"Supera umbral (hipótesis)","No supera (hipótesis)"),"DATOS INCOMPLETOS") -> No supera (hipótesis) | C22: =IF(C13<>"DATOS INCOMPLETOS",IF(C21>=Supuestos!$B$7,"Supera umbral (hipótesis)","No supera (hipótesis)"),"DATOS INCOMPLETOS") -> Supera umbral (hipótesis) | D22: =IF(D13<>"DATOS INCOMPLETOS",IF(D21>=Supuestos!$B$7,"Supera umbral (hipótesis)","No supera (hipótesis)"),"DATOS INCOMPLETOS") -> Supera umbral (hipótesis) | E22: =IF(E13<>"DATOS INCOMPLETOS",IF(E21>=Supuestos!$B$7,"Supera umbral (hipótesis)","No supera (hipótesis)"),"DATOS INCOMPLETOS") -> Supera umbral (hipótesis) | F22: =IF(F13<>"DATOS INCOMPLETOS",IF(F21>=Supuestos!$B$7,"Supera umbral (hipótesis)","No supera (hipótesis)"),"DATOS INCOMPLETOS") -> Supera umbral (hipótesis) | G22: =IF(G13<>"DATOS INCOMPLETOS",IF(G21>=Supuestos!$B$7,"Supera umbral","No supera"),"DATOS INCOMPLETOS") -> DATOS INCOMPLETOS
A23: Contribución tras CAC de referencia | B23: =IF(B13<>"DATOS INCOMPLETOS",B21-Supuestos!$B$9,"DATOS INCOMPLETOS") -> -9.4435876 | C23: =IF(C13<>"DATOS INCOMPLETOS",C21-Supuestos!$B$9,"DATOS INCOMPLETOS") -> -2.9563562 | D23: =IF(D13<>"DATOS INCOMPLETOS",D21-Supuestos!$B$9,"DATOS INCOMPLETOS") -> 1.5436438 | E23: =IF(E13<>"DATOS INCOMPLETOS",E21-Supuestos!$B$9,"DATOS INCOMPLETOS") -> 1.0308752 | F23: =IF(F13<>"DATOS INCOMPLETOS",F21-Supuestos!$B$9,"DATOS INCOMPLETOS") -> -2.8563562 | G23: =IF(G13<>"DATOS INCOMPLETOS",G21-Supuestos!$B$9,"DATOS INCOMPLETOS") -> DATOS INCOMPLETOS
A24: Pedidos financiables con el capital (coste completo) | B24: =IF(B13<>"DATOS INCOMPLETOS",INT(Supuestos!$B$8/B14),"DATOS INCOMPLETOS") -> 3 | C24: =IF(C13<>"DATOS INCOMPLETOS",INT(Supuestos!$B$8/C14),"DATOS INCOMPLETOS") -> 3 | D24: =IF(D13<>"DATOS INCOMPLETOS",INT(Supuestos!$B$8/D14),"DATOS INCOMPLETOS") -> 5 | E24: =IF(E13<>"DATOS INCOMPLETOS",INT(Supuestos!$B$8/E14),"DATOS INCOMPLETOS") -> 3 | F24: =IF(F13<>"DATOS INCOMPLETOS",INT(Supuestos!$B$8/F14),"DATOS INCOMPLETOS") -> 3 | G24: =IF(G13<>"DATOS INCOMPLETOS",INT(Supuestos!$B$8/G14),"DATOS INCOMPLETOS") -> DATOS INCOMPLETOS
A26: Notas
A27: Fila 13: el fallo de la V1 era IF(SUM(G6:G10)>0,SUM,agregado): con 1 de 5 partidas tomaba ese importe como coste total e inflaba el margen. Ahora 1–4 partidas = DATOS INCOMPLETOS.
A28: Filas 16–17 de las hipótesis valen 0 para reproducir los informes. En REAL deben rellenarse (0 solo si es real).
A29: Ningún veredicto dice «rentable»: superar el umbral antes de marketing no implica beneficio (ver fila 23).

Sheet Test de precio
A1: Test de precio con el mismo coste (hipótesis — no son precios decididos)
A2: Coste usado: | B2: =IF(Escenarios!G13="COMPLETO",Escenarios!G14,Escenarios!C14) -> 14 | C2: =IF(Escenarios!G13="COMPLETO","REAL","HIPÓTESIS: coste del escenario Base") -> HIPÓTESIS: coste del escenario Base
A3: Reserva incidencias: | B3: =IF(Escenarios!G13="COMPLETO",Escenarios!G15,Escenarios!C15) -> 2.5
A5: PVP con IVA (a probar) | B5: PVP sin IVA | C5: Comisión | D5: Contribución | E5: Veredicto | F5: Tras CAC ref.
A6: 24.9 | B6: =A6/(1+Supuestos!$B$4) -> 20.578512 | C6: =A6*Supuestos!$B$5+Supuestos!$B$6 -> 1.0221 | D6: =B6-$B$2-$B$3-C6 -> 3.0564124 | E6: =IF(D6>=Supuestos!$B$7,"Supera umbral","No supera")&IF($C$2="REAL",""," (hipótesis)") -> No supera (hipótesis) | F6: =D6-Supuestos!$B$9 -> -6.9435876
A7: 29.9 | B7: =A7/(1+Supuestos!$B$4) -> 24.710744 | C7: =A7*Supuestos!$B$5+Supuestos!$B$6 -> 1.1671 | D7: =B7-$B$2-$B$3-C7 -> 7.0436438 | E7: =IF(D7>=Supuestos!$B$7,"Supera umbral","No supera")&IF($C$2="REAL",""," (hipótesis)") -> Supera umbral (hipótesis) | F7: =D7-Supuestos!$B$9 -> -2.9563562
A8: 34.9 | B8: =A8/(1+Supuestos!$B$4) -> 28.842975 | C8: =A8*Supuestos!$B$5+Supuestos!$B$6 -> 1.3121 | D8: =B8-$B$2-$B$3-C8 -> 11.030875 | E8: =IF(D8>=Supuestos!$B$7,"Supera umbral","No supera")&IF($C$2="REAL",""," (hipótesis)") -> Supera umbral (hipótesis) | F8: =D8-Supuestos!$B$9 -> 1.0308752

Sheet Capital circulante
A1: Capital necesario antes de cobrar las liquidaciones
A3: Concepto | B3: Valor | C3: Nota
A4: Pedidos por día (hipótesis) | B4: 1 | C4: Editar: escenario de ventas a cubrir
A5: Días hasta cobrar | B5: =Supuestos!B10 -> 5
A6: Coste por pedido pagado al proveedor | B6: =IF(Escenarios!G13="COMPLETO",Escenarios!G14,Escenarios!C14) -> 14 | C6: =IF(Escenarios!G13="COMPLETO","REAL","HIPÓTESIS (Base)") -> HIPÓTESIS (Base)
A7: Colchón para reembolsos (pedidos equivalentes) | B7: 2 | C7: Hipótesis
A8: Capital necesario | B8: =B4*B5*B6+B7*B6 -> 98
A9: Capital disponible | B9: =Supuestos!B8 -> 50
A10: ¿Suficiente? | B10: =IF(B9>=B8,"Sí","INSUFICIENTE") -> INSUFICIENTE
A11: Pedidos/día sostenibles sin capital extra | B11: =IF(B5*B6=0,"—",MAX(0,(B9-B7*B6)/(B5*B6))) -> 0.31428571

Sheet Panel semanal
A1: Panel semanal (rellenar con datos de Shopify Analytics; sin datos = vacío)
A3: Semana | B3: Sesiones | C3: Sesiones con vista de producto | D3: Sesiones con ATC | E3: Sesiones con checkout | F3: Pedidos | G3: Ventas brutas (€) | H3: Gasto de captación (€) | I3: Coste de contenido (€) | J3: Devoluciones (nº) | K3: Conversión tienda | L3: ATC / vistas producto | M3: Checkout / ATC | N3: AOV | O3: CAC | P3: Contribución estimada | Q3: Tasa devolución
K4: =IF(OR(B4="",B4=0,F4=""),"",F4/B4) | L4: =IF(OR(C4="",C4=0,D4=""),"",D4/C4) | M4: =IF(OR(D4="",D4=0,E4=""),"",E4/D4) | N4: =IF(OR(F4="",F4=0,G4=""),"",G4/F4) | O4: =IF(OR(F4="",F4=0,H4=""),"",(H4+IF(I4="",0,I4))/F4) | P4: =IF(F4="","",IF(Escenarios!$G$13="COMPLETO",F4*Escenarios!$G$21,"DATOS INCOMPLETOS")) | Q4: =IF(OR(F4="",F4=0,J4=""),"",J4/F4)
K5: =IF(OR(B5="",B5=0,F5=""),"",F5/B5) | L5: =IF(OR(C5="",C5=0,D5=""),"",D5/C5) | M5: =IF(OR(D5="",D5=0,E5=""),"",E5/D5) | N5: =IF(OR(F5="",F5=0,G5=""),"",G5/F5) | O5: =IF(OR(F5="",F5=0,H5=""),"",(H5+IF(I5="",0,I5))/F5) | P5: =IF(F5="","",IF(Escenarios!$G$13="COMPLETO",F5*Escenarios!$G$21,"DATOS INCOMPLETOS")) | Q5: =IF(OR(F5="",F5=0,J5=""),"",J5/F5)
K6: =IF(OR(B6="",B6=0,F6=""),"",F6/B6) | L6: =IF(OR(C6="",C6=0,D6=""),"",D6/C6) | M6: =IF(OR(D6="",D6=0,E6=""),"",E6/D6) | N6: =IF(OR(F6="",F6=0,G6=""),"",G6/F6) | O6: =IF(OR(F6="",F6=0,H6=""),"",(H6+IF(I6="",0,I6))/F6) | P6: =IF(F6="","",IF(Escenarios!$G$13="COMPLETO",F6*Escenarios!$G$21,"DATOS INCOMPLETOS")) | Q6: =IF(OR(F6="",F6=0,J6=""),"",J6/F6)
K7: =IF(OR(B7="",B7=0,F7=""),"",F7/B7) | L7: =IF(OR(C7="",C7=0,D7=""),"",D7/C7) | M7: =IF(OR(D7="",D7=0,E7=""),"",E7/D7) | N7: =IF(OR(F7="",F7=0,G7=""),"",G7/F7) | O7: =IF(OR(F7="",F7=0,H7=""),"",(H7+IF(I7="",0,I7))/F7) | P7: =IF(F7="","",IF(Escenarios!$G$13="COMPLETO",F7*Escenarios!$G$21,"DATOS INCOMPLETOS")) | Q7: =IF(OR(F7="",F7=0,J7=""),"",J7/F7)
K8: =IF(OR(B8="",B8=0,F8=""),"",F8/B8) | L8: =IF(OR(C8="",C8=0,D8=""),"",D8/C8) | M8: =IF(OR(D8="",D8=0,E8=""),"",E8/D8) | N8: =IF(OR(F8="",F8=0,G8=""),"",G8/F8) | O8: =IF(OR(F8="",F8=0,H8=""),"",(H8+IF(I8="",0,I8))/F8) | P8: =IF(F8="","",IF(Escenarios!$G$13="COMPLETO",F8*Escenarios!$G$21,"DATOS INCOMPLETOS")) | Q8: =IF(OR(F8="",F8=0,J8=""),"",J8/F8)
K9: =IF(OR(B9="",B9=0,F9=""),"",F9/B9) | L9: =IF(OR(C9="",C9=0,D9=""),"",D9/C9) | M9: =IF(OR(D9="",D9=0,E9=""),"",E9/D9) | N9: =IF(OR(F9="",F9=0,G9=""),"",G9/F9) | O9: =IF(OR(F9="",F9=0,H9=""),"",(H9+IF(I9="",0,I9))/F9) | P9: =IF(F9="","",IF(Escenarios!$G$13="COMPLETO",F9*Escenarios!$G$21,"DATOS INCOMPLETOS")) | Q9: =IF(OR(F9="",F9=0,J9=""),"",J9/F9)
K10: =IF(OR(B10="",B10=0,F10=""),"",F10/B10) | L10: =IF(OR(C10="",C10=0,D10=""),"",D10/C10) | M10: =IF(OR(D10="",D10=0,E10=""),"",E10/D10) | N10: =IF(OR(F10="",F10=0,G10=""),"",G10/F10) | O10: =IF(OR(F10="",F10=0,H10=""),"",(H10+IF(I10="",0,I10))/F10) | P10: =IF(F10="","",IF(Escenarios!$G$13="COMPLETO",F10*Escenarios!$G$21,"DATOS INCOMPLETOS")) | Q10: =IF(OR(F10="",F10=0,J10=""),"",J10/F10)
K11: =IF(OR(B11="",B11=0,F11=""),"",F11/B11) | L11: =IF(OR(C11="",C11=0,D11=""),"",D11/C11) | M11: =IF(OR(D11="",D11=0,E11=""),"",E11/D11) | N11: =IF(OR(F11="",F11=0,G11=""),"",G11/F11) | O11: =IF(OR(F11="",F11=0,H11=""),"",(H11+IF(I11="",0,I11))/F11) | P11: =IF(F11="","",IF(Escenarios!$G$13="COMPLETO",F11*Escenarios!$G$21,"DATOS INCOMPLETOS")) | Q11: =IF(OR(F11="",F11=0,J11=""),"",J11/F11)
K12: =IF(OR(B12="",B12=0,F12=""),"",F12/B12) | L12: =IF(OR(C12="",C12=0,D12=""),"",D12/C12) | M12: =IF(OR(D12="",D12=0,E12=""),"",E12/D12) | N12: =IF(OR(F12="",F12=0,G12=""),"",G12/F12) | O12: =IF(OR(F12="",F12=0,H12=""),"",(H12+IF(I12="",0,I12))/F12) | P12: =IF(F12="","",IF(Escenarios!$G$13="COMPLETO",F12*Escenarios!$G$21,"DATOS INCOMPLETOS")) | Q12: =IF(OR(F12="",F12=0,J12=""),"",J12/F12)
K13: =IF(OR(B13="",B13=0,F13=""),"",F13/B13) | L13: =IF(OR(C13="",C13=0,D13=""),"",D13/C13) | M13: =IF(OR(D13="",D13=0,E13=""),"",E13/D13) | N13: =IF(OR(F13="",F13=0,G13=""),"",G13/F13) | O13: =IF(OR(F13="",F13=0,H13=""),"",(H13+IF(I13="",0,I13))/F13) | P13: =IF(F13="","",IF(Escenarios!$G$13="COMPLETO",F13*Escenarios!$G$21,"DATOS INCOMPLETOS")) | Q13: =IF(OR(F13="",F13=0,J13=""),"",J13/F13)
K14: =IF(OR(B14="",B14=0,F14=""),"",F14/B14) | L14: =IF(OR(C14="",C14=0,D14=""),"",D14/C14) | M14: =IF(OR(D14="",D14=0,E14=""),"",E14/D14) | N14: =IF(OR(F14="",F14=0,G14=""),"",G14/F14) | O14: =IF(OR(F14="",F14=0,H14=""),"",(H14+IF(I14="",0,I14))/F14) | P14: =IF(F14="","",IF(Escenarios!$G$13="COMPLETO",F14*Escenarios!$G$21,"DATOS INCOMPLETOS")) | Q14: =IF(OR(F14="",F14=0,J14=""),"",J14/F14)
K15: =IF(OR(B15="",B15=0,F15=""),"",F15/B15) | L15: =IF(OR(C15="",C15=0,D15=""),"",D15/C15) | M15: =IF(OR(D15="",D15=0,E15=""),"",E15/D15) | N15: =IF(OR(F15="",F15=0,G15=""),"",G15/F15) | O15: =IF(OR(F15="",F15=0,H15=""),"",(H15+IF(I15="",0,I15))/F15) | P15: =IF(F15="","",IF(Escenarios!$G$13="COMPLETO",F15*Escenarios!$G$21,"DATOS INCOMPLETOS")) | Q15: =IF(OR(F15="",F15=0,J15=""),"",J15/F15)
A17: Definiciones: conversión = pedidos/sesiones · ATC = sesiones con añadir al carrito / sesiones con vista de producto · Checkout = sesiones con checkout / sesiones con ATC · AOV = ventas brutas / pedidos · CAC = (captación + contenido) / pedidos. Las visualizaciones en redes NO son sesiones.

Sheet Sensibilidad
A1: Sensibilidad de adquisición (hipótesis de planificación)
A2: Contribución usada: | C2: =IF(Escenarios!G13="COMPLETO",Escenarios!G21,Escenarios!C21) -> 7.0436438 | D2: =IF(Escenarios!G13="COMPLETO","REAL","HIPÓTESIS (Base)") -> HIPÓTESIS (Base)
A4: Sesiones cualificadas/mes | B4: Conversión hipotética | C4: Pedidos teóricos | D4: Contribución total | E4: Capital a adelantar
A5: 300 | B5: 0.005 | C5: =A5*B5 -> 1.5 | D5: =C5*$C$2 -> 10.565466 | E5: =C5*'Capital circulante'!$B$6 -> 21
A6: 1000 | B6: 0.01 | C6: =A6*B6 -> 10 | D6: =C6*$C$2 -> 70.436438 | E6: =C6*'Capital circulante'!$B$6 -> 140
A7: 3000 | B7: 0.01 | C7: =A7*B7 -> 30 | D7: =C7*$C$2 -> 211.30931 | E7: =C7*'Capital circulante'!$B$6 -> 420
A8: 10000 | B8: 0.015 | C8: =A8*B8 -> 150 | D8: =C8*$C$2 -> 1056.5466 | E8: =C8*'Capital circulante'!$B$6 -> 2100
