Workbook

Sheet Leyenda
A1: Economía unitaria · Prototipo «Descanso Compartido»
A2: Fecha: 13/10/2026 · Estado: NO-GO. Ninguna cifra de este libro es un coste real ni una previsión de beneficio.
A4: Cómo usarlo
A5: 1. Celdas con fondo AMARILLO y texto AZUL = datos que debéis rellenar o cambiar.
A6: 2. Texto NEGRO = fórmulas. No las sobrescribáis.
A7: 3. Columna «REAL» de la hoja Escenarios: vacía a propósito. Rellenadla SOLO con cotizaciones firmadas (DP-07).
A8: 4. Los escenarios 1–5 reproducen los ejemplos HIPOTÉTICOS de los informes (Estudio §9.2 y Maestro §09).
A10: Fuentes de los supuestos
A11: IVA 21 %: tipo general (Agencia Tributaria, S25). El tipo aplicable al SKU está SIN CONFIRMAR (DP-22).
A12: Comisión 2,9 % + 0,30 €: supuesto prudencial de los informes, NO tarifa contractual de Shopify (S26).
A13: Reserva de incidencias y umbral de 7–8 €: criterio analítico del Estudio §9.2, no datos observados.
A14: Capital 50 €: presupuesto declarado por el titular.
A15: Excluido: cuota Shopify, apps, gestoría, IRPF, devoluciones extraordinarias, publicidad, deducibilidad del IVA soportado.

Sheet Supuestos
A1: Supuestos globales
A3: Supuesto | B3: Valor | C3: Fuente / nota
A4: IVA aplicado al PVP (hipótesis) | B4: 0.21 | C4: S25: tipo general. Tipo del SKU sin clasificar (DP-22).
A5: Comisión de pago variable (hipótesis) | B5: 0.029 | C5: Supuesto de los informes; confirmar tarifa real (DP-11).
A6: Comisión de pago fija por pedido (hipótesis) | B6: 0.3 | C6: Supuesto de los informes.
A7: Umbral mínimo de contribución antes de marketing | B7: 7 | C7: Estudio §9.2: no avanzar por debajo de 7–8 €.
A8: Capital disponible para pedidos y reembolsos | B8: 50 | C8: Presupuesto declarado por el titular.
A9: CAC de referencia para comparar (hipótesis) | B9: 10 | C9: Estudio §9.2: ejemplo de CAC de 10 €.

Sheet Escenarios
A1: Contribución por pedido (antes de costes fijos, marketing e impuestos directos)
A3: Concepto | B3: 1. Desfavorable | C3: 2. Base exploración | D3: 3. Mejor logística | E3: 4. PVP superior | F3: 5. Ejemplo Maestro | G3: REAL (cotización firmada)
A4: PVP con IVA | B4: 24.9 | C4: 29.9 | D4: 29.9 | E4: 34.9 | F4: 29.9
A5: Coste completo puesto en cliente (agregado, hipótesis) | B5: 16 | C5: 14 | D5: 10 | E5: 14 | F5: 14.4
A6: · Producto (desglose real)
A7: · Envío a domicilio (desglose real)
A8: · Aranceles / derecho 3 € / importación
A9: · Preparación y embalaje
A10: · Otros costes variables no recuperables
A11: Coste completo usado | B11: =IF(SUM(B6:B10)>0,SUM(B6:B10),B5) -> 16 | C11: =IF(SUM(C6:C10)>0,SUM(C6:C10),C5) -> 14 | D11: =IF(SUM(D6:D10)>0,SUM(D6:D10),D5) -> 10 | E11: =IF(SUM(E6:E10)>0,SUM(E6:E10),E5) -> 14 | F11: =IF(SUM(F6:F10)>0,SUM(F6:F10),F5) -> 14.4 | G11: =IF(SUM(G6:G10)>0,SUM(G6:G10),G5) -> 0
A12: Reserva por devoluciones, soporte e incidencias | B12: 3 | C12: 2.5 | D12: 2 | E12: 2.5 | F12: 2
A13: PVP sin IVA | B13: =IF(B4="","",B4/(1+Supuestos!$B$4)) -> 20.578512 | C13: =IF(C4="","",C4/(1+Supuestos!$B$4)) -> 24.710744 | D13: =IF(D4="","",D4/(1+Supuestos!$B$4)) -> 24.710744 | E13: =IF(E4="","",E4/(1+Supuestos!$B$4)) -> 28.842975 | F13: =IF(F4="","",F4/(1+Supuestos!$B$4)) -> 24.710744 | G13: =IF(G4="","",G4/(1+Supuestos!$B$4))
A14: Comisión de pago | B14: =IF(B4="","",B4*Supuestos!$B$5+Supuestos!$B$6) -> 1.0221 | C14: =IF(C4="","",C4*Supuestos!$B$5+Supuestos!$B$6) -> 1.1671 | D14: =IF(D4="","",D4*Supuestos!$B$5+Supuestos!$B$6) -> 1.1671 | E14: =IF(E4="","",E4*Supuestos!$B$5+Supuestos!$B$6) -> 1.3121 | F14: =IF(F4="","",F4*Supuestos!$B$5+Supuestos!$B$6) -> 1.1671 | G14: =IF(G4="","",G4*Supuestos!$B$5+Supuestos!$B$6)
A15: Contribución por pedido | B15: =IF(B4="","",B13-B11-B12-B14) -> 0.5564124 | C15: =IF(C4="","",C13-C11-C12-C14) -> 7.0436438 | D15: =IF(D4="","",D13-D11-D12-D14) -> 11.543644 | E15: =IF(E4="","",E13-E11-E12-E14) -> 11.030875 | F15: =IF(F4="","",F13-F11-F12-F14) -> 7.1436438 | G15: =IF(G4="","",G13-G11-G12-G14)
A16: ¿Supera el umbral mínimo? | B16: =IF(B4="","Sin datos",IF(B15>=Supuestos!$B$7,"Sí","NO")) -> NO | C16: =IF(C4="","Sin datos",IF(C15>=Supuestos!$B$7,"Sí","NO")) -> Sí | D16: =IF(D4="","Sin datos",IF(D15>=Supuestos!$B$7,"Sí","NO")) -> Sí | E16: =IF(E4="","Sin datos",IF(E15>=Supuestos!$B$7,"Sí","NO")) -> Sí | F16: =IF(F4="","Sin datos",IF(F15>=Supuestos!$B$7,"Sí","NO")) -> Sí | G16: =IF(G4="","Sin datos",IF(G15>=Supuestos!$B$7,"Sí","NO")) -> Sin datos
A17: Contribución tras CAC de referencia | B17: =IF(B4="","",B15-Supuestos!$B$9) -> -9.4435876 | C17: =IF(C4="","",C15-Supuestos!$B$9) -> -2.9563562 | D17: =IF(D4="","",D15-Supuestos!$B$9) -> 1.5436438 | E17: =IF(E4="","",E15-Supuestos!$B$9) -> 1.0308752 | F17: =IF(F4="","",F15-Supuestos!$B$9) -> -2.8563562 | G17: =IF(G4="","",G15-Supuestos!$B$9)
A18: Pedidos completos financiables con el capital | B18: =IF(B11>0,INT(Supuestos!$B$8/B11),"Sin datos") -> 3 | C18: =IF(C11>0,INT(Supuestos!$B$8/C11),"Sin datos") -> 3 | D18: =IF(D11>0,INT(Supuestos!$B$8/D11),"Sin datos") -> 5 | E18: =IF(E11>0,INT(Supuestos!$B$8/E11),"Sin datos") -> 3 | F18: =IF(F11>0,INT(Supuestos!$B$8/F11),"Sin datos") -> 3 | G18: =IF(G11>0,INT(Supuestos!$B$8/G11),"Sin datos") -> Sin datos
A20: Notas
A21: Escenarios 1–4: Estudio §9.2 (resultado publicado: 0,56 / 7,04 / 11,54 / 11,03 €). Escenario 5: Maestro §09 (7,14 €). Todos HIPOTÉTICOS.
A22: Columna REAL: déjala vacía hasta tener cotizaciones firmadas. Si rellenas el desglose (filas 6–10), sustituye al coste agregado.
A23: Fila 18: con 50 € y un proveedor que cobra al instante, solo se financian 3 pedidos a 14 € (Estudio §9.3).

Sheet Sensibilidad
A1: Sensibilidad de adquisición (hipótesis de planificación, no previsión)
A2: Contribución usada (escenario base, enlazada): | C2: =Escenarios!C15 -> 7.0436438
A4: Sesiones cualificadas/mes | B4: Conversión hipotética | C4: Pedidos teóricos | D4: Contribución total | E4: Capital a adelantar (coste base)
A5: 300 | B5: 0.005 | C5: =A5*B5 -> 1.5 | D5: =C5*$C$2 -> 10.565466 | E5: =C5*Escenarios!$C$11 -> 21
A6: 1000 | B6: 0.01 | C6: =A6*B6 -> 10 | D6: =C6*$C$2 -> 70.436438 | E6: =C6*Escenarios!$C$11 -> 140
A7: 3000 | B7: 0.01 | C7: =A7*B7 -> 30 | D7: =C7*$C$2 -> 211.30931 | E7: =C7*Escenarios!$C$11 -> 420
A8: 10000 | B8: 0.015 | C8: =A8*B8 -> 150 | D8: =C8*$C$2 -> 1056.5466 | E8: =C8*Escenarios!$C$11 -> 2100
A10: Pedidos fraccionarios = valor esperado matemático (Estudio §9.5). Las conversiones NO son benchmarks del nicho.
